Metadata-Version: 1.0
Name: confine
Version: 17.7.1
Summary: identifying disease module
Home-page: https://github.com/asherameli/confine
Author: Asher Ameli
Author-email: aameli@bwh.harvard.edu
License: no reuse
Platform: UNKNOWN
